[
  {
    "Id": "69234031",
    "IsSection": false,
    "IsVideoURL": false,
    "IsImage": false,
    "IsWarmup": false,
    "IsGymnastics": false,
    "IsWeightlifting": false,
    "IsMetcon": false,
    "IsWeightliftingTotal": false,
    "Name": "Warm Up",
    "Comment": "",
    "VideoURL": "",
    "VideoURLComment": "",
    "ImageURL": "",
    "ImageFilename": "",
    "ImageComment": "",
    "PrefixText": "",
    "MeasureIsMaxEffort": false,
    "MeasureRepScheme": "",
    "Description": "<table width=\"388\"><tbody><tr height=\"280\"><td width=\"388\" height=\"280\"><p>RD 1<br />Jog 200m<br />3 Burpees<br />3 DB Snatch<br />5 box step overs<br /><br />RD 2<br />Run 200m<br />3 Single DB Devils Press<br />5 Box Jump Overs<br /><br />RD 3<br />Sprint 200m<br />3 Double DB Devils Press<br />5 Burpee Box Jump Overs</p><p> </p><p> </p></td></tr></tbody></table>",
    "Rounds": 0,
    "ResultTypeId": 0,
    "IsResultTypeEachRound": false,
    "IsResultTypeNoMeasure": true,
    "IsResultTypeCheckmark": false,
    "EachRoundTypeLabel": "",
    "ScalingId": 2,
    "ComponentId": "27470364",
    "TotalWeightLiftingComponents": {
      "List": [],
      "EmptyListItem": ""
    },
    "WorkoutComponentResults": {
      "List": [
        {
          "ClassId": "125883694",
          "StartTime": "06:15:00",
          "HasResultsForClass": false,
          "PerformanceResultId": "0",
          "FullyFormattedResult": "",
          "IsRx": false,
          "IsRxPlus": false
        }
      ]
    },
    "HasPerformedAtLeastOnce": false,
    "HasAtLeastOneWorkoutComponentResult": false
  },
  {
    "Id": "69234039",
    "IsSection": false,
    "IsVideoURL": false,
    "IsImage": false,
    "IsWarmup": false,
    "IsGymnastics": false,
    "IsWeightlifting": false,
    "IsMetcon": false,
    "IsWeightliftingTotal": false,
    "Name": "Metcon",
    "Comment": "",
    "VideoURL": "",
    "VideoURLComment": "",
    "ImageURL": "",
    "ImageFilename": "",
    "ImageComment": "",
    "PrefixText": "",
    "MeasureIsMaxEffort": false,
    "MeasureRepScheme": "",
    "Description": "<table width=\"388\"><tbody><tr height=\"477\"><td width=\"388\" height=\"477\"><p>4 rounds, 4 mins each, for max reps of:<br />Run 200m<br />12 Devil Press, 22.5/15kg<br />max reps in remaining time Burpee Box Jump Overs, 24/20 in<br /><br />Rest 1 min between each round.</p><p> </p><p> </p></td></tr></tbody></table>",
    "Rounds": 0,
    "ResultTypeId": 0,
    "IsResultTypeEachRound": false,
    "IsResultTypeNoMeasure": false,
    "IsResultTypeCheckmark": false,
    "EachRoundTypeLabel": "",
    "ScalingId": 2,
    "ComponentId": "27470367",
    "TotalWeightLiftingComponents": {
      "List": [],
      "EmptyListItem": ""
    },
    "WorkoutComponentResults": {
      "List": [
        {
          "ClassId": "125883694",
          "StartTime": "06:15:00",
          "HasResultsForClass": false,
          "PerformanceResultId": "0",
          "FullyFormattedResult": "",
          "IsRx": false,
          "IsRxPlus": false
        }
      ]
    },
    "HasPerformedAtLeastOnce": false,
    "HasAtLeastOneWorkoutComponentResult": false
  },
  {
    "Id": "69234042",
    "IsSection": false,
    "IsVideoURL": false,
    "IsImage": false,
    "IsWarmup": false,
    "IsGymnastics": false,
    "IsWeightlifting": false,
    "IsMetcon": false,
    "IsWeightliftingTotal": false,
    "Name": "Metcon",
    "Comment": "",
    "VideoURL": "",
    "VideoURLComment": "",
    "ImageURL": "",
    "ImageFilename": "",
    "ImageComment": "",
    "PrefixText": "",
    "MeasureIsMaxEffort": false,
    "MeasureRepScheme": "",
    "Description": "<table width=\"388\"><tbody><tr height=\"93\"><td width=\"388\" height=\"93\"><p>4 rounds for quality of:<br />5 L/5 R Seated Single Arm Dumbbell Strict Press, pick load<br />10 DB Bent Over Rows, pick load<br />Kettlebell Farmers + Waiters Carry, pick load, L+R 15m/R+L 15m</p><p> </p><p> </p></td></tr></tbody></table>",
    "Rounds": 0,
    "ResultTypeId": 0,
    "IsResultTypeEachRound": false,
    "IsResultTypeNoMeasure": true,
    "IsResultTypeCheckmark": false,
    "EachRoundTypeLabel": "",
    "ScalingId": 2,
    "ComponentId": "27470370",
    "TotalWeightLiftingComponents": {
      "List": [],
      "EmptyListItem": ""
    },
    "WorkoutComponentResults": {
      "List": [
        {
          "ClassId": "125883694",
          "StartTime": "06:15:00",
          "HasResultsForClass": false,
          "PerformanceResultId": "0",
          "FullyFormattedResult": "",
          "IsRx": false,
          "IsRxPlus": false
        }
      ]
    },
    "HasPerformedAtLeastOnce": false,
    "HasAtLeastOneWorkoutComponentResult": false
  },
  {
    "Id": "69234045",
    "IsSection": true,
    "IsVideoURL": false,
    "IsImage": false,
    "IsWarmup": false,
    "IsGymnastics": false,
    "IsWeightlifting": false,
    "IsMetcon": false,
    "IsWeightliftingTotal": false,
    "Name": "Extra Work",
    "Comment": "",
    "VideoURL": "",
    "VideoURLComment": "",
    "ImageURL": "",
    "ImageFilename": "",
    "ImageComment": "",
    "PrefixText": "",
    "MeasureIsMaxEffort": false,
    "MeasureRepScheme": "",
    "Description": "",
    "Rounds": 0,
    "ResultTypeId": 0,
    "IsResultTypeEachRound": false,
    "IsResultTypeNoMeasure": false,
    "IsResultTypeCheckmark": false,
    "EachRoundTypeLabel": "",
    "ScalingId": 0,
    "ComponentId": "0",
    "TotalWeightLiftingComponents": {
      "List": [],
      "EmptyListItem": ""
    },
    "WorkoutComponentResults": {
      "List": [
        {
          "ClassId": "125883694",
          "StartTime": "06:15:00",
          "HasResultsForClass": false,
          "PerformanceResultId": "0",
          "FullyFormattedResult": "",
          "IsRx": false,
          "IsRxPlus": false
        }
      ]
    },
    "HasPerformedAtLeastOnce": false,
    "HasAtLeastOneWorkoutComponentResult": false
  },
  {
    "Id": "69234056",
    "IsSection": true,
    "IsVideoURL": false,
    "IsImage": false,
    "IsWarmup": false,
    "IsGymnastics": false,
    "IsWeightlifting": false,
    "IsMetcon": false,
    "IsWeightliftingTotal": false,
    "Name": "Weightlifting",
    "Comment": "",
    "VideoURL": "",
    "VideoURLComment": "",
    "ImageURL": "",
    "ImageFilename": "",
    "ImageComment": "",
    "PrefixText": "",
    "MeasureIsMaxEffort": false,
    "MeasureRepScheme": "",
    "Description": "",
    "Rounds": 0,
    "ResultTypeId": 0,
    "IsResultTypeEachRound": false,
    "IsResultTypeNoMeasure": false,
    "IsResultTypeCheckmark": false,
    "EachRoundTypeLabel": "",
    "ScalingId": 0,
    "ComponentId": "0",
    "TotalWeightLiftingComponents": {
      "List": [],
      "EmptyListItem": ""
    },
    "WorkoutComponentResults": {
      "List": [
        {
          "ClassId": "125883694",
          "StartTime": "06:15:00",
          "HasResultsForClass": false,
          "PerformanceResultId": "0",
          "FullyFormattedResult": "",
          "IsRx": false,
          "IsRxPlus": false
        }
      ]
    },
    "HasPerformedAtLeastOnce": false,
    "HasAtLeastOneWorkoutComponentResult": false
  },
  {
    "Id": "69234054",
    "IsSection": false,
    "IsVideoURL": false,
    "IsImage": false,
    "IsWarmup": false,
    "IsGymnastics": false,
    "IsWeightlifting": true,
    "IsMetcon": false,
    "IsWeightliftingTotal": false,
    "Name": "Snatch Pull",
    "Comment": "<table width=\"388\"><tbody><tr height=\"453\"><td width=\"388\" height=\"453\"><p>3-3-3-3<br /><br />Use the heaviest weight you can for each set.<br /><br />*Rest 2-3 mins between sets.<br /><br />Set 1: 100% 1RM Snatch<br />Set 2: 100% 1RM Snatch<br />Set 3: 105+% 1RM Snatch<br />Set 4: 105+% 1RM Snatch<br /><br />Athlete Notes<br />Try to go heavier than last week but do not compromise technique.</p><p> </p><p> </p></td></tr></tbody></table>",
    "VideoURL": "",
    "VideoURLComment": "",
    "ImageURL": "",
    "ImageFilename": "",
    "ImageComment": "",
    "PrefixText": "",
    "MeasureIsMaxEffort": false,
    "MeasureRepScheme": "3-3-3-3",
    "Description": "",
    "Rounds": 0,
    "ResultTypeId": 0,
    "IsResultTypeEachRound": false,
    "IsResultTypeNoMeasure": false,
    "IsResultTypeCheckmark": false,
    "EachRoundTypeLabel": "",
    "ScalingId": 2,
    "ComponentId": "58",
    "TotalWeightLiftingComponents": {
      "List": [],
      "EmptyListItem": ""
    },
    "WorkoutComponentResults": {
      "List": [
        {
          "ClassId": "125883694",
          "StartTime": "06:15:00",
          "HasResultsForClass": false,
          "PerformanceResultId": "0",
          "FullyFormattedResult": "",
          "IsRx": false,
          "IsRxPlus": false
        }
      ]
    },
    "HasPerformedAtLeastOnce": false,
    "HasAtLeastOneWorkoutComponentResult": false
  },
  {
    "Id": "69234060",
    "IsSection": true,
    "IsVideoURL": false,
    "IsImage": false,
    "IsWarmup": false,
    "IsGymnastics": false,
    "IsWeightlifting": false,
    "IsMetcon": false,
    "IsWeightliftingTotal": false,
    "Name": "Aerobic Conditioning",
    "Comment": "",
    "VideoURL": "",
    "VideoURLComment": "",
    "ImageURL": "",
    "ImageFilename": "",
    "ImageComment": "",
    "PrefixText": "",
    "MeasureIsMaxEffort": false,
    "MeasureRepScheme": "",
    "Description": "",
    "Rounds": 0,
    "ResultTypeId": 0,
    "IsResultTypeEachRound": false,
    "IsResultTypeNoMeasure": false,
    "IsResultTypeCheckmark": false,
    "EachRoundTypeLabel": "",
    "ScalingId": 0,
    "ComponentId": "0",
    "TotalWeightLiftingComponents": {
      "List": [],
      "EmptyListItem": ""
    },
    "WorkoutComponentResults": {
      "List": [
        {
          "ClassId": "125883694",
          "StartTime": "06:15:00",
          "HasResultsForClass": false,
          "PerformanceResultId": "0",
          "FullyFormattedResult": "",
          "IsRx": false,
          "IsRxPlus": false
        }
      ]
    },
    "HasPerformedAtLeastOnce": false,
    "HasAtLeastOneWorkoutComponentResult": false
  },
  {
    "Id": "69234064",
    "IsSection": false,
    "IsVideoURL": false,
    "IsImage": false,
    "IsWarmup": false,
    "IsGymnastics": false,
    "IsWeightlifting": false,
    "IsMetcon": false,
    "IsWeightliftingTotal": false,
    "Name": "Metcon",
    "Comment": "",
    "VideoURL": "",
    "VideoURLComment": "",
    "ImageURL": "",
    "ImageFilename": "",
    "ImageComment": "",
    "PrefixText": "",
    "MeasureIsMaxEffort": false,
    "MeasureRepScheme": "",
    "Description": "<table width=\"388\"><tbody><tr height=\"90\"><td width=\"388\" height=\"90\">Go every 5 mins:<br />Ski Erg: 6x 1000 m<br /><br />Each for time.</td></tr></tbody></table>",
    "Rounds": 0,
    "ResultTypeId": 0,
    "IsResultTypeEachRound": false,
    "IsResultTypeNoMeasure": false,
    "IsResultTypeCheckmark": false,
    "EachRoundTypeLabel": "",
    "ScalingId": 2,
    "ComponentId": "27470377",
    "TotalWeightLiftingComponents": {
      "List": [],
      "EmptyListItem": ""
    },
    "WorkoutComponentResults": {
      "List": [
        {
          "ClassId": "125883694",
          "StartTime": "06:15:00",
          "HasResultsForClass": false,
          "PerformanceResultId": "0",
          "FullyFormattedResult": "",
          "IsRx": false,
          "IsRxPlus": false
        }
      ]
    },
    "HasPerformedAtLeastOnce": false,
    "HasAtLeastOneWorkoutComponentResult": false
  }
]