[
  {
    "Id": "72052871",
    "IsSection": false,
    "IsVideoURL": false,
    "IsImage": false,
    "IsWarmup": false,
    "IsGymnastics": false,
    "IsWeightlifting": false,
    "IsMetcon": false,
    "IsWeightliftingTotal": false,
    "Name": "Warm Up",
    "Comment": "",
    "VideoURL": "",
    "VideoURLComment": "",
    "ImageURL": "",
    "ImageFilename": "",
    "ImageComment": "",
    "PrefixText": "",
    "MeasureIsMaxEffort": false,
    "MeasureRepScheme": "",
    "Description": "<p>Warm-up<br />3 rounds for quality of:<br />Jog 200m<br />Bodyweight Walking Lunge, 50 ft<br />10 Plate Snatches, 15/10kg<br />20 Alternating Lateral Line Jumps</p>",
    "Rounds": 0,
    "ResultTypeId": 6,
    "IsResultTypeEachRound": false,
    "IsResultTypeNoMeasure": true,
    "IsResultTypeCheckmark": false,
    "EachRoundTypeLabel": "",
    "ScalingId": 2,
    "ComponentId": "28475296",
    "ComponentExternalURL": "",
    "ComponentSystemComment": "",
    "TotalWeightLiftingComponents": {
      "List": [],
      "EmptyListItem": ""
    },
    "WorkoutComponentResults": {
      "List": [],
      "EmptyListItem": {
        "ClassId": "0",
        "StartTime": "",
        "HasResultsForClass": false,
        "PerformanceResultId": "0",
        "FullyFormattedResult": "",
        "IsRx": false,
        "IsRxPlus": false
      }
    },
    "HasPerformedAtLeastOnce": false,
    "HasAtLeastOneWorkoutComponentResult": false
  },
  {
    "Id": "72068788",
    "IsSection": false,
    "IsVideoURL": false,
    "IsImage": false,
    "IsWarmup": false,
    "IsGymnastics": false,
    "IsWeightlifting": false,
    "IsMetcon": false,
    "IsWeightliftingTotal": false,
    "Name": "Metcon",
    "Comment": "",
    "VideoURL": "",
    "VideoURLComment": "",
    "ImageURL": "",
    "ImageFilename": "",
    "ImageComment": "",
    "PrefixText": "",
    "MeasureIsMaxEffort": false,
    "MeasureRepScheme": "",
    "Description": "<p>For time:<br />50 Toes-to-bars<br />-- then --<br />3 rounds of:<br />14/11 Row Calories<br />14 Dumbbell Push Press, 22.5kg/15kg<br />14 Burpee Box Jump Overs, 24/20 in<br />-- then --<br />50 Toes-to-bars</p>",
    "Rounds": 0,
    "ResultTypeId": 2,
    "IsResultTypeEachRound": false,
    "IsResultTypeNoMeasure": false,
    "IsResultTypeCheckmark": false,
    "EachRoundTypeLabel": "",
    "ScalingId": 2,
    "ComponentId": "28480840",
    "ComponentExternalURL": "",
    "ComponentSystemComment": "",
    "TotalWeightLiftingComponents": {
      "List": [],
      "EmptyListItem": ""
    },
    "WorkoutComponentResults": {
      "List": [],
      "EmptyListItem": {
        "ClassId": "0",
        "StartTime": "",
        "HasResultsForClass": false,
        "PerformanceResultId": "0",
        "FullyFormattedResult": "",
        "IsRx": false,
        "IsRxPlus": false
      }
    },
    "HasPerformedAtLeastOnce": false,
    "HasAtLeastOneWorkoutComponentResult": false
  },
  {
    "Id": "72117814",
    "IsSection": false,
    "IsVideoURL": false,
    "IsImage": false,
    "IsWarmup": false,
    "IsGymnastics": false,
    "IsWeightlifting": false,
    "IsMetcon": false,
    "IsWeightliftingTotal": false,
    "Name": "Metcon",
    "Comment": "",
    "VideoURL": "",
    "VideoURLComment": "",
    "ImageURL": "",
    "ImageFilename": "",
    "ImageComment": "",
    "PrefixText": "",
    "MeasureIsMaxEffort": false,
    "MeasureRepScheme": "",
    "Description": "<p>“At Home”<br /><br />For time:<br />50 Sit Ups<br />-- then --<br />3 rounds of:<br />Run 200m<br />14 Handstand Push Ups<br />14 Burpee’s<br />-- then --<br />50 Sit Ups</p>",
    "Rounds": 0,
    "ResultTypeId": 2,
    "IsResultTypeEachRound": false,
    "IsResultTypeNoMeasure": false,
    "IsResultTypeCheckmark": false,
    "EachRoundTypeLabel": "",
    "ScalingId": 2,
    "ComponentId": "28498138",
    "ComponentExternalURL": "",
    "ComponentSystemComment": "",
    "TotalWeightLiftingComponents": {
      "List": [],
      "EmptyListItem": ""
    },
    "WorkoutComponentResults": {
      "List": [],
      "EmptyListItem": {
        "ClassId": "0",
        "StartTime": "",
        "HasResultsForClass": false,
        "PerformanceResultId": "0",
        "FullyFormattedResult": "",
        "IsRx": false,
        "IsRxPlus": false
      }
    },
    "HasPerformedAtLeastOnce": false,
    "HasAtLeastOneWorkoutComponentResult": false
  },
  {
    "Id": "72097143",
    "IsSection": true,
    "IsVideoURL": false,
    "IsImage": false,
    "IsWarmup": false,
    "IsGymnastics": false,
    "IsWeightlifting": false,
    "IsMetcon": false,
    "IsWeightliftingTotal": false,
    "Name": "Extra Work",
    "Comment": "",
    "VideoURL": "",
    "VideoURLComment": "",
    "ImageURL": "",
    "ImageFilename": "",
    "ImageComment": "",
    "PrefixText": "",
    "MeasureIsMaxEffort": false,
    "MeasureRepScheme": "",
    "Description": "",
    "Rounds": 0,
    "ResultTypeId": 0,
    "IsResultTypeEachRound": false,
    "IsResultTypeNoMeasure": false,
    "IsResultTypeCheckmark": false,
    "EachRoundTypeLabel": "",
    "ScalingId": 0,
    "ComponentId": "0",
    "ComponentExternalURL": "",
    "ComponentSystemComment": "",
    "TotalWeightLiftingComponents": {
      "List": [],
      "EmptyListItem": ""
    },
    "WorkoutComponentResults": {
      "List": [],
      "EmptyListItem": {
        "ClassId": "0",
        "StartTime": "",
        "HasResultsForClass": false,
        "PerformanceResultId": "0",
        "FullyFormattedResult": "",
        "IsRx": false,
        "IsRxPlus": false
      }
    },
    "HasPerformedAtLeastOnce": false,
    "HasAtLeastOneWorkoutComponentResult": false
  },
  {
    "Id": "72117739",
    "IsSection": true,
    "IsVideoURL": false,
    "IsImage": false,
    "IsWarmup": false,
    "IsGymnastics": false,
    "IsWeightlifting": false,
    "IsMetcon": false,
    "IsWeightliftingTotal": false,
    "Name": "Weightlifting",
    "Comment": "",
    "VideoURL": "",
    "VideoURLComment": "",
    "ImageURL": "",
    "ImageFilename": "",
    "ImageComment": "",
    "PrefixText": "",
    "MeasureIsMaxEffort": false,
    "MeasureRepScheme": "",
    "Description": "",
    "Rounds": 0,
    "ResultTypeId": 0,
    "IsResultTypeEachRound": false,
    "IsResultTypeNoMeasure": false,
    "IsResultTypeCheckmark": false,
    "EachRoundTypeLabel": "",
    "ScalingId": 0,
    "ComponentId": "0",
    "ComponentExternalURL": "",
    "ComponentSystemComment": "",
    "TotalWeightLiftingComponents": {
      "List": [],
      "EmptyListItem": ""
    },
    "WorkoutComponentResults": {
      "List": [],
      "EmptyListItem": {
        "ClassId": "0",
        "StartTime": "",
        "HasResultsForClass": false,
        "PerformanceResultId": "0",
        "FullyFormattedResult": "",
        "IsRx": false,
        "IsRxPlus": false
      }
    },
    "HasPerformedAtLeastOnce": false,
    "HasAtLeastOneWorkoutComponentResult": false
  },
  {
    "Id": "72117740",
    "IsSection": true,
    "IsVideoURL": false,
    "IsImage": false,
    "IsWarmup": false,
    "IsGymnastics": false,
    "IsWeightlifting": false,
    "IsMetcon": false,
    "IsWeightliftingTotal": false,
    "Name": "Strength",
    "Comment": "",
    "VideoURL": "",
    "VideoURLComment": "",
    "ImageURL": "",
    "ImageFilename": "",
    "ImageComment": "",
    "PrefixText": "",
    "MeasureIsMaxEffort": false,
    "MeasureRepScheme": "",
    "Description": "",
    "Rounds": 0,
    "ResultTypeId": 0,
    "IsResultTypeEachRound": false,
    "IsResultTypeNoMeasure": false,
    "IsResultTypeCheckmark": false,
    "EachRoundTypeLabel": "",
    "ScalingId": 0,
    "ComponentId": "0",
    "ComponentExternalURL": "",
    "ComponentSystemComment": "",
    "TotalWeightLiftingComponents": {
      "List": [],
      "EmptyListItem": ""
    },
    "WorkoutComponentResults": {
      "List": [],
      "EmptyListItem": {
        "ClassId": "0",
        "StartTime": "",
        "HasResultsForClass": false,
        "PerformanceResultId": "0",
        "FullyFormattedResult": "",
        "IsRx": false,
        "IsRxPlus": false
      }
    },
    "HasPerformedAtLeastOnce": false,
    "HasAtLeastOneWorkoutComponentResult": false
  },
  {
    "Id": "72117732",
    "IsSection": false,
    "IsVideoURL": false,
    "IsImage": false,
    "IsWarmup": false,
    "IsGymnastics": false,
    "IsWeightlifting": false,
    "IsMetcon": false,
    "IsWeightliftingTotal": false,
    "Name": "Clean + Low Hang Clean + Hang Clean",
    "Comment": "",
    "VideoURL": "",
    "VideoURLComment": "",
    "ImageURL": "",
    "ImageFilename": "",
    "ImageComment": "",
    "PrefixText": "",
    "MeasureIsMaxEffort": false,
    "MeasureRepScheme": "",
    "Description": "<p>1x [ 1 Clean + 1 Low Hang Clean + 1 Hang Clean ], 70% 1RM<br />1x [ 1 Clean + 1 Low Hang Clean + 1 Hang Clean ], 70% 1RM<br />1x [ 1 Clean + 1 Low Hang Clean + 1 Hang Clean ], 75% 1RM<br />1x [ 1 Clean + 1 Low Hang Clean + 1 Hang Clean ], 75% 1RM<br />1x [ 1 Clean + 1 Low Hang Clean + 1 Hang Clean ], 75% 1RM<br /><br />Rest as needed between sets.</p>",
    "Rounds": 0,
    "ResultTypeId": 10,
    "IsResultTypeEachRound": false,
    "IsResultTypeNoMeasure": false,
    "IsResultTypeCheckmark": false,
    "EachRoundTypeLabel": "For Weight",
    "ScalingId": 2,
    "ComponentId": "28498097",
    "ComponentExternalURL": "",
    "ComponentSystemComment": "",
    "TotalWeightLiftingComponents": {
      "List": [],
      "EmptyListItem": ""
    },
    "WorkoutComponentResults": {
      "List": [],
      "EmptyListItem": {
        "ClassId": "0",
        "StartTime": "",
        "HasResultsForClass": false,
        "PerformanceResultId": "0",
        "FullyFormattedResult": "",
        "IsRx": false,
        "IsRxPlus": false
      }
    },
    "HasPerformedAtLeastOnce": false,
    "HasAtLeastOneWorkoutComponentResult": false
  },
  {
    "Id": "72117746",
    "IsSection": false,
    "IsVideoURL": false,
    "IsImage": false,
    "IsWarmup": false,
    "IsGymnastics": false,
    "IsWeightlifting": true,
    "IsMetcon": false,
    "IsWeightliftingTotal": false,
    "Name": "Back Squat",
    "Comment": "<p>Back Squat 6x2 at 80% 1RM<br /><br />Rest as needed between sets.</p>",
    "VideoURL": "",
    "VideoURLComment": "",
    "ImageURL": "",
    "ImageFilename": "",
    "ImageComment": "",
    "PrefixText": "",
    "MeasureIsMaxEffort": false,
    "MeasureRepScheme": "2-2-2-2-2-2",
    "Description": "",
    "Rounds": 0,
    "ResultTypeId": 1,
    "IsResultTypeEachRound": false,
    "IsResultTypeNoMeasure": false,
    "IsResultTypeCheckmark": false,
    "EachRoundTypeLabel": "",
    "ScalingId": 2,
    "ComponentId": "22",
    "ComponentExternalURL": "",
    "ComponentSystemComment": "",
    "TotalWeightLiftingComponents": {
      "List": [],
      "EmptyListItem": ""
    },
    "WorkoutComponentResults": {
      "List": [],
      "EmptyListItem": {
        "ClassId": "0",
        "StartTime": "",
        "HasResultsForClass": false,
        "PerformanceResultId": "0",
        "FullyFormattedResult": "",
        "IsRx": false,
        "IsRxPlus": false
      }
    },
    "HasPerformedAtLeastOnce": true,
    "HasAtLeastOneWorkoutComponentResult": false
  }
]