[
  {
    "Id": "74261658",
    "IsSection": false,
    "IsVideoURL": false,
    "IsImage": false,
    "IsWarmup": false,
    "IsGymnastics": false,
    "IsWeightlifting": false,
    "IsMetcon": false,
    "IsWeightliftingTotal": false,
    "Name": "Warm Up",
    "Comment": "",
    "VideoURL": "",
    "VideoURLComment": "",
    "ImageURL": "",
    "ImageFilename": "",
    "ImageComment": "",
    "PrefixText": "",
    "MeasureIsMaxEffort": false,
    "MeasureRepScheme": "",
    "Description": "<p>3 rounds for quality of:<br />10 L/10 R Banded External Shoulder Rotations<br />10 L/10 R Banded Internal Shoulder Rotations<br />10 Bstrict beat swings<br />5 Pause Tabletop Bridges, 2-3 secs<br />10 Barbell Romanian Deadlifts<br />5 No-Dip Muscle Cleans<br />5 Front Squats</p>",
    "Rounds": 0,
    "ResultTypeId": 6,
    "IsResultTypeEachRound": false,
    "IsResultTypeNoMeasure": true,
    "IsResultTypeCheckmark": false,
    "EachRoundTypeLabel": "",
    "ScalingId": 2,
    "ComponentId": "29279887",
    "ComponentExternalURL": "",
    "ComponentSystemComment": "",
    "TotalWeightLiftingComponents": {
      "List": [],
      "EmptyListItem": ""
    },
    "WorkoutComponentResults": {
      "List": [
        {
          "ClassId": "130313994",
          "StartTime": "07:00:00",
          "HasResultsForClass": false,
          "PerformanceResultId": "0",
          "FullyFormattedResult": "",
          "IsRx": false,
          "IsRxPlus": false
        }
      ]
    },
    "HasPerformedAtLeastOnce": false,
    "HasAtLeastOneWorkoutComponentResult": false
  },
  {
    "Id": "74261666",
    "IsSection": false,
    "IsVideoURL": false,
    "IsImage": false,
    "IsWarmup": false,
    "IsGymnastics": false,
    "IsWeightlifting": false,
    "IsMetcon": false,
    "IsWeightliftingTotal": false,
    "Name": "Metcon",
    "Comment": "",
    "VideoURL": "",
    "VideoURLComment": "",
    "ImageURL": "",
    "ImageFilename": "",
    "ImageComment": "",
    "PrefixText": "",
    "MeasureIsMaxEffort": false,
    "MeasureRepScheme": "",
    "Description": "<p>3 rounds for time of:<br />3 Rope Climbs, 15 ft<br />15 Front Squats, 52/38kg<br />7 Burpee Pull Ups<br />15 Deadlifts, 52/38kg<br />7 Wall Walks<br /><br /><br />RX+:<br />3 rounds for time of:<br />5 Rope Climbs, 15 ft<br />15 Front Squats, 61/43kg<br />7 Burpee Bar Muscle-ups<br />15 Deadlifts, 61/43kg<br />7 Wall Walks</p>",
    "Rounds": 0,
    "ResultTypeId": 10,
    "IsResultTypeEachRound": false,
    "IsResultTypeNoMeasure": false,
    "IsResultTypeCheckmark": false,
    "EachRoundTypeLabel": "For Time",
    "ScalingId": 3,
    "ComponentId": "29279891",
    "ComponentExternalURL": "",
    "ComponentSystemComment": "",
    "TotalWeightLiftingComponents": {
      "List": [],
      "EmptyListItem": ""
    },
    "WorkoutComponentResults": {
      "List": [
        {
          "ClassId": "130313994",
          "StartTime": "07:00:00",
          "HasResultsForClass": false,
          "PerformanceResultId": "0",
          "FullyFormattedResult": "",
          "IsRx": false,
          "IsRxPlus": false
        }
      ]
    },
    "HasPerformedAtLeastOnce": false,
    "HasAtLeastOneWorkoutComponentResult": false
  },
  {
    "Id": "74261668",
    "IsSection": true,
    "IsVideoURL": false,
    "IsImage": false,
    "IsWarmup": false,
    "IsGymnastics": false,
    "IsWeightlifting": false,
    "IsMetcon": false,
    "IsWeightliftingTotal": false,
    "Name": "Extra Work ",
    "Comment": "",
    "VideoURL": "",
    "VideoURLComment": "",
    "ImageURL": "",
    "ImageFilename": "",
    "ImageComment": "",
    "PrefixText": "",
    "MeasureIsMaxEffort": false,
    "MeasureRepScheme": "",
    "Description": "",
    "Rounds": 0,
    "ResultTypeId": 0,
    "IsResultTypeEachRound": false,
    "IsResultTypeNoMeasure": false,
    "IsResultTypeCheckmark": false,
    "EachRoundTypeLabel": "",
    "ScalingId": 0,
    "ComponentId": "0",
    "ComponentExternalURL": "",
    "ComponentSystemComment": "",
    "TotalWeightLiftingComponents": {
      "List": [],
      "EmptyListItem": ""
    },
    "WorkoutComponentResults": {
      "List": [
        {
          "ClassId": "130313994",
          "StartTime": "07:00:00",
          "HasResultsForClass": false,
          "PerformanceResultId": "0",
          "FullyFormattedResult": "",
          "IsRx": false,
          "IsRxPlus": false
        }
      ]
    },
    "HasPerformedAtLeastOnce": false,
    "HasAtLeastOneWorkoutComponentResult": false
  },
  {
    "Id": "74261672",
    "IsSection": true,
    "IsVideoURL": false,
    "IsImage": false,
    "IsWarmup": false,
    "IsGymnastics": false,
    "IsWeightlifting": false,
    "IsMetcon": false,
    "IsWeightliftingTotal": false,
    "Name": "Durability",
    "Comment": "",
    "VideoURL": "",
    "VideoURLComment": "",
    "ImageURL": "",
    "ImageFilename": "",
    "ImageComment": "",
    "PrefixText": "",
    "MeasureIsMaxEffort": false,
    "MeasureRepScheme": "",
    "Description": "",
    "Rounds": 0,
    "ResultTypeId": 0,
    "IsResultTypeEachRound": false,
    "IsResultTypeNoMeasure": false,
    "IsResultTypeCheckmark": false,
    "EachRoundTypeLabel": "",
    "ScalingId": 0,
    "ComponentId": "0",
    "ComponentExternalURL": "",
    "ComponentSystemComment": "",
    "TotalWeightLiftingComponents": {
      "List": [],
      "EmptyListItem": ""
    },
    "WorkoutComponentResults": {
      "List": [
        {
          "ClassId": "130313994",
          "StartTime": "07:00:00",
          "HasResultsForClass": false,
          "PerformanceResultId": "0",
          "FullyFormattedResult": "",
          "IsRx": false,
          "IsRxPlus": false
        }
      ]
    },
    "HasPerformedAtLeastOnce": false,
    "HasAtLeastOneWorkoutComponentResult": false
  },
  {
    "Id": "74261686",
    "IsSection": false,
    "IsVideoURL": false,
    "IsImage": false,
    "IsWarmup": false,
    "IsGymnastics": false,
    "IsWeightlifting": false,
    "IsMetcon": false,
    "IsWeightliftingTotal": false,
    "Name": "Metcon",
    "Comment": "",
    "VideoURL": "",
    "VideoURLComment": "",
    "ImageURL": "",
    "ImageFilename": "",
    "ImageComment": "",
    "PrefixText": "",
    "MeasureIsMaxEffort": false,
    "MeasureRepScheme": "",
    "Description": "<p>Every 1 min for 9 mins, alternating between:<br />10 Prone Dumbbell Rows, pick load<br />Sandbag Carry, pick load, 30m<br />12 Dumbbell Hammer Curls, pick load</p>",
    "Rounds": 0,
    "ResultTypeId": 6,
    "IsResultTypeEachRound": false,
    "IsResultTypeNoMeasure": true,
    "IsResultTypeCheckmark": false,
    "EachRoundTypeLabel": "",
    "ScalingId": 2,
    "ComponentId": "29279897",
    "ComponentExternalURL": "",
    "ComponentSystemComment": "",
    "TotalWeightLiftingComponents": {
      "List": [],
      "EmptyListItem": ""
    },
    "WorkoutComponentResults": {
      "List": [
        {
          "ClassId": "130313994",
          "StartTime": "07:00:00",
          "HasResultsForClass": false,
          "PerformanceResultId": "0",
          "FullyFormattedResult": "",
          "IsRx": false,
          "IsRxPlus": false
        }
      ]
    },
    "HasPerformedAtLeastOnce": false,
    "HasAtLeastOneWorkoutComponentResult": false
  },
  {
    "Id": "74261687",
    "IsSection": false,
    "IsVideoURL": false,
    "IsImage": false,
    "IsWarmup": false,
    "IsGymnastics": false,
    "IsWeightlifting": false,
    "IsMetcon": false,
    "IsWeightliftingTotal": false,
    "Name": "Aerobic Capacity",
    "Comment": "",
    "VideoURL": "",
    "VideoURLComment": "",
    "ImageURL": "",
    "ImageFilename": "",
    "ImageComment": "",
    "PrefixText": "",
    "MeasureIsMaxEffort": false,
    "MeasureRepScheme": "",
    "Description": "<p>Each for distance:<br />Bike Erg, 1 min<br />Bike Erg, 2 mins<br />Bike Erg, 1 min<br />Bike Erg, 2 mins<br />Bike Erg, 1 min<br />Bike Erg, 2 mins<br />-- Rest 4 mins --<br />Bike Erg, 1 min<br />Bike Erg, 2 mins<br />Bike Erg, 1 min<br />Bike Erg, 2 mins<br />Bike Erg, 1 min<br />Bike Erg, 2 mins<br />-- Rest 4 mins --<br />Bike Erg, 1 min<br />Bike Erg, 2 mins<br />Bike Erg, 1 min<br />Bike Erg, 2 mins<br />Bike Erg, 1 min<br />Bike Erg, 2 mins.<br /><br />Complete as 3 sets of 3 rounds:<br />1 min- 120-125% FTP<br />2 mins- 88-92% FTP<br />Rest 4 mins- active spinning, 60-65% FTP</p>",
    "Rounds": 0,
    "ResultTypeId": 10,
    "IsResultTypeEachRound": false,
    "IsResultTypeNoMeasure": false,
    "IsResultTypeCheckmark": false,
    "EachRoundTypeLabel": "For Distance",
    "ScalingId": 2,
    "ComponentId": "29279898",
    "ComponentExternalURL": "",
    "ComponentSystemComment": "",
    "TotalWeightLiftingComponents": {
      "List": [],
      "EmptyListItem": ""
    },
    "WorkoutComponentResults": {
      "List": [
        {
          "ClassId": "130313994",
          "StartTime": "07:00:00",
          "HasResultsForClass": false,
          "PerformanceResultId": "0",
          "FullyFormattedResult": "",
          "IsRx": false,
          "IsRxPlus": false
        }
      ]
    },
    "HasPerformedAtLeastOnce": false,
    "HasAtLeastOneWorkoutComponentResult": false
  },
  {
    "Id": "74261691",
    "IsSection": false,
    "IsVideoURL": false,
    "IsImage": false,
    "IsWarmup": false,
    "IsGymnastics": false,
    "IsWeightlifting": false,
    "IsMetcon": false,
    "IsWeightliftingTotal": false,
    "Name": "Gymnastic Conditioning",
    "Comment": "",
    "VideoURL": "",
    "VideoURLComment": "",
    "ImageURL": "",
    "ImageFilename": "",
    "ImageComment": "",
    "PrefixText": "",
    "MeasureIsMaxEffort": false,
    "MeasureRepScheme": "",
    "Description": "<p>Accumulate 2mins<br />Freestanding Headstand<br /><br />Then 3 rounds<br />5 Strict TTB<br />30s Star plank ES https://youtu.be/p634cOd5Eyk</p>",
    "Rounds": 0,
    "ResultTypeId": 2,
    "IsResultTypeEachRound": false,
    "IsResultTypeNoMeasure": false,
    "IsResultTypeCheckmark": false,
    "EachRoundTypeLabel": "",
    "ScalingId": 2,
    "ComponentId": "29279900",
    "ComponentExternalURL": "",
    "ComponentSystemComment": "",
    "TotalWeightLiftingComponents": {
      "List": [],
      "EmptyListItem": ""
    },
    "WorkoutComponentResults": {
      "List": [
        {
          "ClassId": "130313994",
          "StartTime": "07:00:00",
          "HasResultsForClass": false,
          "PerformanceResultId": "0",
          "FullyFormattedResult": "",
          "IsRx": false,
          "IsRxPlus": false
        }
      ]
    },
    "HasPerformedAtLeastOnce": false,
    "HasAtLeastOneWorkoutComponentResult": false
  },
  {
    "Id": "74261693",
    "IsSection": false,
    "IsVideoURL": true,
    "IsImage": false,
    "IsWarmup": false,
    "IsGymnastics": false,
    "IsWeightlifting": false,
    "IsMetcon": false,
    "IsWeightliftingTotal": false,
    "Name": "",
    "Comment": "",
    "VideoURL": "https://youtu.be/p634cOd5Eyk",
    "VideoURLComment": "",
    "ImageURL": "",
    "ImageFilename": "",
    "ImageComment": "",
    "PrefixText": "",
    "MeasureIsMaxEffort": false,
    "MeasureRepScheme": "",
    "Description": "",
    "Rounds": 0,
    "ResultTypeId": 0,
    "IsResultTypeEachRound": false,
    "IsResultTypeNoMeasure": false,
    "IsResultTypeCheckmark": false,
    "EachRoundTypeLabel": "",
    "ScalingId": 0,
    "ComponentId": "0",
    "ComponentExternalURL": "",
    "ComponentSystemComment": "",
    "TotalWeightLiftingComponents": {
      "List": [],
      "EmptyListItem": ""
    },
    "WorkoutComponentResults": {
      "List": [
        {
          "ClassId": "130313994",
          "StartTime": "07:00:00",
          "HasResultsForClass": false,
          "PerformanceResultId": "0",
          "FullyFormattedResult": "",
          "IsRx": false,
          "IsRxPlus": false
        }
      ]
    },
    "HasPerformedAtLeastOnce": false,
    "HasAtLeastOneWorkoutComponentResult": false
  }
]