[
  {
    "Id": "72948328",
    "IsSection": false,
    "IsVideoURL": false,
    "IsImage": false,
    "IsWarmup": false,
    "IsGymnastics": false,
    "IsWeightlifting": false,
    "IsMetcon": false,
    "IsWeightliftingTotal": false,
    "Name": "Warm Up",
    "Comment": "",
    "VideoURL": "",
    "VideoURLComment": "",
    "ImageURL": "",
    "ImageFilename": "",
    "ImageComment": "",
    "PrefixText": "",
    "MeasureIsMaxEffort": false,
    "MeasureRepScheme": "",
    "Description": "<p>Warm-up<br />3 rounds for quality of:<br />Run 200m<br />Farmers Carry - Front Rack Carry - OH Carry, 30m- light load<br />10 GHD Back Extensions<br />10 Banded Good Mornings</p>",
    "Rounds": 0,
    "ResultTypeId": 6,
    "IsResultTypeEachRound": false,
    "IsResultTypeNoMeasure": true,
    "IsResultTypeCheckmark": false,
    "EachRoundTypeLabel": "",
    "ScalingId": 2,
    "ComponentId": "28788237",
    "ComponentExternalURL": "",
    "ComponentSystemComment": "",
    "TotalWeightLiftingComponents": {
      "List": [],
      "EmptyListItem": ""
    },
    "WorkoutComponentResults": {
      "List": [],
      "EmptyListItem": {
        "ClassId": "0",
        "StartTime": "",
        "HasResultsForClass": false,
        "PerformanceResultId": "0",
        "FullyFormattedResult": "",
        "IsRx": false,
        "IsRxPlus": false
      }
    },
    "HasPerformedAtLeastOnce": false,
    "HasAtLeastOneWorkoutComponentResult": false
  },
  {
    "Id": "72948329",
    "IsSection": false,
    "IsVideoURL": false,
    "IsImage": false,
    "IsWarmup": false,
    "IsGymnastics": false,
    "IsWeightlifting": false,
    "IsMetcon": false,
    "IsWeightliftingTotal": false,
    "Name": "Metcon",
    "Comment": "",
    "VideoURL": "",
    "VideoURLComment": "",
    "ImageURL": "",
    "ImageFilename": "",
    "ImageComment": "",
    "PrefixText": "",
    "MeasureIsMaxEffort": false,
    "MeasureRepScheme": "",
    "Description": "<p>For time:<br />Run, 1000 m<br />50/40 Push-ups<br />Kettlebell Farmers Carry, 24/16kg, 100m<br />50 Kb Swings 24/16kg<br />Run, 1000 m<br />40/32 Push-ups<br />Kettlebell Front Rack Carry, 24/16kg, 50m<br />40 Kb Swings 24/16kg<br />Run, 1000 m<br />30/24 Push-ups<br />Kettlebell Overhead Carry, 24/16kg, 50m<br />30 Kb Swings 24/16kg</p>",
    "Rounds": 0,
    "ResultTypeId": 2,
    "IsResultTypeEachRound": false,
    "IsResultTypeNoMeasure": false,
    "IsResultTypeCheckmark": false,
    "EachRoundTypeLabel": "",
    "ScalingId": 2,
    "ComponentId": "28788238",
    "ComponentExternalURL": "",
    "ComponentSystemComment": "",
    "TotalWeightLiftingComponents": {
      "List": [],
      "EmptyListItem": ""
    },
    "WorkoutComponentResults": {
      "List": [],
      "EmptyListItem": {
        "ClassId": "0",
        "StartTime": "",
        "HasResultsForClass": false,
        "PerformanceResultId": "0",
        "FullyFormattedResult": "",
        "IsRx": false,
        "IsRxPlus": false
      }
    },
    "HasPerformedAtLeastOnce": false,
    "HasAtLeastOneWorkoutComponentResult": false
  },
  {
    "Id": "72948330",
    "IsSection": true,
    "IsVideoURL": false,
    "IsImage": false,
    "IsWarmup": false,
    "IsGymnastics": false,
    "IsWeightlifting": false,
    "IsMetcon": false,
    "IsWeightliftingTotal": false,
    "Name": "Extra Work",
    "Comment": "",
    "VideoURL": "",
    "VideoURLComment": "",
    "ImageURL": "",
    "ImageFilename": "",
    "ImageComment": "",
    "PrefixText": "",
    "MeasureIsMaxEffort": false,
    "MeasureRepScheme": "",
    "Description": "",
    "Rounds": 0,
    "ResultTypeId": 0,
    "IsResultTypeEachRound": false,
    "IsResultTypeNoMeasure": false,
    "IsResultTypeCheckmark": false,
    "EachRoundTypeLabel": "",
    "ScalingId": 0,
    "ComponentId": "0",
    "ComponentExternalURL": "",
    "ComponentSystemComment": "",
    "TotalWeightLiftingComponents": {
      "List": [],
      "EmptyListItem": ""
    },
    "WorkoutComponentResults": {
      "List": [],
      "EmptyListItem": {
        "ClassId": "0",
        "StartTime": "",
        "HasResultsForClass": false,
        "PerformanceResultId": "0",
        "FullyFormattedResult": "",
        "IsRx": false,
        "IsRxPlus": false
      }
    },
    "HasPerformedAtLeastOnce": false,
    "HasAtLeastOneWorkoutComponentResult": false
  },
  {
    "Id": "72948333",
    "IsSection": false,
    "IsVideoURL": true,
    "IsImage": false,
    "IsWarmup": false,
    "IsGymnastics": false,
    "IsWeightlifting": false,
    "IsMetcon": false,
    "IsWeightliftingTotal": false,
    "Name": "",
    "Comment": "",
    "VideoURL": "https://youtu.be/F8o3hOFsrHI",
    "VideoURLComment": "",
    "ImageURL": "",
    "ImageFilename": "",
    "ImageComment": "",
    "PrefixText": "",
    "MeasureIsMaxEffort": false,
    "MeasureRepScheme": "",
    "Description": "",
    "Rounds": 0,
    "ResultTypeId": 0,
    "IsResultTypeEachRound": false,
    "IsResultTypeNoMeasure": false,
    "IsResultTypeCheckmark": false,
    "EachRoundTypeLabel": "",
    "ScalingId": 0,
    "ComponentId": "0",
    "ComponentExternalURL": "",
    "ComponentSystemComment": "",
    "TotalWeightLiftingComponents": {
      "List": [],
      "EmptyListItem": ""
    },
    "WorkoutComponentResults": {
      "List": [],
      "EmptyListItem": {
        "ClassId": "0",
        "StartTime": "",
        "HasResultsForClass": false,
        "PerformanceResultId": "0",
        "FullyFormattedResult": "",
        "IsRx": false,
        "IsRxPlus": false
      }
    },
    "HasPerformedAtLeastOnce": false,
    "HasAtLeastOneWorkoutComponentResult": false
  },
  {
    "Id": "72948332",
    "IsSection": false,
    "IsVideoURL": false,
    "IsImage": false,
    "IsWarmup": false,
    "IsGymnastics": false,
    "IsWeightlifting": false,
    "IsMetcon": false,
    "IsWeightliftingTotal": false,
    "Name": "Metcon",
    "Comment": "",
    "VideoURL": "",
    "VideoURLComment": "",
    "ImageURL": "",
    "ImageFilename": "",
    "ImageComment": "",
    "PrefixText": "",
    "MeasureIsMaxEffort": false,
    "MeasureRepScheme": "",
    "Description": "<p>Every 3 mins for 9 mins do:<br />4 L/4 R Turkish Get-ups, pick load<br />12 Dumbbell Chest Flies, pick load<br />10x [ 1 JM Press + 1 Rollback Extension ], pick load<br /><br />* 1 JM Press + 1 Rollback Extension - https://youtu.be/F8o3hOFsrHI</p>",
    "Rounds": 0,
    "ResultTypeId": 10,
    "IsResultTypeEachRound": false,
    "IsResultTypeNoMeasure": false,
    "IsResultTypeCheckmark": false,
    "EachRoundTypeLabel": "For Weight",
    "ScalingId": 2,
    "ComponentId": "28788240",
    "ComponentExternalURL": "",
    "ComponentSystemComment": "",
    "TotalWeightLiftingComponents": {
      "List": [],
      "EmptyListItem": ""
    },
    "WorkoutComponentResults": {
      "List": [],
      "EmptyListItem": {
        "ClassId": "0",
        "StartTime": "",
        "HasResultsForClass": false,
        "PerformanceResultId": "0",
        "FullyFormattedResult": "",
        "IsRx": false,
        "IsRxPlus": false
      }
    },
    "HasPerformedAtLeastOnce": false,
    "HasAtLeastOneWorkoutComponentResult": false
  }
]