[
  {
    "Id": "91354441",
    "IsSection": false,
    "IsVideoURL": false,
    "IsImage": false,
    "IsWarmup": false,
    "IsGymnastics": false,
    "IsWeightlifting": false,
    "IsMetcon": true,
    "IsWeightliftingTotal": false,
    "Name": "Warm Up",
    "Comment": "",
    "VideoURL": "",
    "VideoURLComment": "",
    "ImageURL": "",
    "ImageFilename": "",
    "ImageComment": "",
    "PrefixText": "",
    "MeasureIsMaxEffort": false,
    "MeasureRepScheme": "",
    "Description": "<p>20 Calf Pumps</p><p>20 Calf Raises</p><p>10 Banded Scap Retractions</p><p>100m Run</p><p>5 Inchworm to push up</p><p> </p><p>Then:</p><p>3 Rounds</p><p>5 Suitcase Deadlifts</p><p>5 Single Arm DB Cleans</p><p>5 Single Arm Shoulder to overhead</p><p>30 Seconds of Skipping</p>",
    "Rounds": 0,
    "ResultTypeId": 6,
    "IsResultTypeEachRound": false,
    "IsResultTypeNoMeasure": true,
    "IsResultTypeCheckmark": false,
    "EachRoundTypeLabel": "",
    "ScalingId": 2,
    "ComponentId": "36145940",
    "ComponentExternalURL": "",
    "ComponentSystemComment": "",
    "TotalWeightLiftingComponents": {
      "List": [],
      "EmptyListItem": ""
    },
    "WorkoutComponentResults": {
      "List": [],
      "EmptyListItem": {
        "ClassId": "0",
        "StartTime": "",
        "HasResultsForClass": false,
        "PerformanceResultId": "0",
        "FullyFormattedResult": "",
        "IsRx": false,
        "IsRxPlus": false,
        "HasBeenScored": false
      }
    },
    "HasPerformedAtLeastOnce": false,
    "HasAtLeastOneWorkoutComponentResult": false
  },
  {
    "Id": "91353985",
    "IsSection": true,
    "IsVideoURL": false,
    "IsImage": false,
    "IsWarmup": false,
    "IsGymnastics": false,
    "IsWeightlifting": false,
    "IsMetcon": false,
    "IsWeightliftingTotal": false,
    "Name": "Extra Work",
    "Comment": "",
    "VideoURL": "",
    "VideoURLComment": "",
    "ImageURL": "",
    "ImageFilename": "",
    "ImageComment": "",
    "PrefixText": "",
    "MeasureIsMaxEffort": false,
    "MeasureRepScheme": "",
    "Description": "",
    "Rounds": 0,
    "ResultTypeId": 0,
    "IsResultTypeEachRound": false,
    "IsResultTypeNoMeasure": false,
    "IsResultTypeCheckmark": false,
    "EachRoundTypeLabel": "",
    "ScalingId": 0,
    "ComponentId": "0",
    "ComponentExternalURL": "",
    "ComponentSystemComment": "",
    "TotalWeightLiftingComponents": {
      "List": [],
      "EmptyListItem": ""
    },
    "WorkoutComponentResults": {
      "List": [],
      "EmptyListItem": {
        "ClassId": "0",
        "StartTime": "",
        "HasResultsForClass": false,
        "PerformanceResultId": "0",
        "FullyFormattedResult": "",
        "IsRx": false,
        "IsRxPlus": false,
        "HasBeenScored": false
      }
    },
    "HasPerformedAtLeastOnce": false,
    "HasAtLeastOneWorkoutComponentResult": false
  },
  {
    "Id": "91354396",
    "IsSection": false,
    "IsVideoURL": false,
    "IsImage": false,
    "IsWarmup": false,
    "IsGymnastics": false,
    "IsWeightlifting": false,
    "IsMetcon": true,
    "IsWeightliftingTotal": false,
    "Name": "Metcon",
    "Comment": "<p> </p><p>Score: Max Calories each round</p>",
    "VideoURL": "",
    "VideoURLComment": "",
    "ImageURL": "",
    "ImageFilename": "",
    "ImageComment": "",
    "PrefixText": "",
    "MeasureIsMaxEffort": false,
    "MeasureRepScheme": "",
    "Description": "<p>6 Rounds, 3 Mins each</p><p> </p><p>40 Double Unders</p><p>7 Double DB Deadlift 22.5/15kg</p><p>6 Double DB Hang Power Clean 22.5/15kg</p><p>5 Double DB Shoulder to overhead 22.5/15kg</p><p>4 Double DB Devils Press 22.5/15kg</p><p> </p><p>Max Reps in remaining time Machine Calories</p><p> </p><p>1 Minute Rest</p><p> </p><p>RX+ 30 Drag Rope Double Unders</p>",
    "Rounds": 6,
    "ResultTypeId": 10,
    "IsResultTypeEachRound": true,
    "IsResultTypeNoMeasure": false,
    "IsResultTypeCheckmark": false,
    "EachRoundTypeLabel": "For Calories",
    "ScalingId": 3,
    "ComponentId": "36145916",
    "ComponentExternalURL": "",
    "ComponentSystemComment": "",
    "TotalWeightLiftingComponents": {
      "List": [],
      "EmptyListItem": ""
    },
    "WorkoutComponentResults": {
      "List": [],
      "EmptyListItem": {
        "ClassId": "0",
        "StartTime": "",
        "HasResultsForClass": false,
        "PerformanceResultId": "0",
        "FullyFormattedResult": "",
        "IsRx": false,
        "IsRxPlus": false,
        "HasBeenScored": false
      }
    },
    "HasPerformedAtLeastOnce": false,
    "HasAtLeastOneWorkoutComponentResult": false
  },
  {
    "Id": "91354022",
    "IsSection": false,
    "IsVideoURL": false,
    "IsImage": false,
    "IsWarmup": false,
    "IsGymnastics": false,
    "IsWeightlifting": false,
    "IsMetcon": true,
    "IsWeightliftingTotal": false,
    "Name": "Recovery Stretches 2",
    "Comment": "",
    "VideoURL": "",
    "VideoURLComment": "",
    "ImageURL": "",
    "ImageFilename": "",
    "ImageComment": "",
    "PrefixText": "",
    "MeasureIsMaxEffort": false,
    "MeasureRepScheme": "",
    "Description": "<p>1:00 Childs Pose<br>1:00/1:00 Low Dragon Stretch<br>1:00/1:00 Scorpion Stretch<br>:30/:30 Thread the Needle Stretch<br>5/5 Side Lying Thoracic Rotations</p><ul><li><a target=\"_blank\" rel=\"noopener noreferrer\" href=\"https://www.youtube.com/watch?v=2pkLUbN34GI\">Childs Pose</a></li><li><a target=\"_blank\" rel=\"noopener noreferrer\" href=\"https://www.youtube.com/watch?v=vIbx23Nk4q4\">Low Dragon Stretch</a></li><li><a target=\"_blank\" rel=\"noopener noreferrer\" href=\"https://www.youtube.com/watch?v=NSLDV4N5Gl4\">Scorpion Stretch</a></li><li><a target=\"_blank\" rel=\"noopener noreferrer\" href=\"https://www.youtube.com/watch?v=MfUx9FCOb1E\">Thread the Needle Stretch</a></li><li><a target=\"_blank\" rel=\"noopener noreferrer\" href=\"https://www.youtube.com/watch?v=EHZJns1bXPM\">Side Lying Thoracic Rotations</a></li></ul>",
    "Rounds": 0,
    "ResultTypeId": 6,
    "IsResultTypeEachRound": false,
    "IsResultTypeNoMeasure": true,
    "IsResultTypeCheckmark": false,
    "EachRoundTypeLabel": "",
    "ScalingId": 2,
    "ComponentId": "35679886",
    "ComponentExternalURL": "",
    "ComponentSystemComment": "",
    "TotalWeightLiftingComponents": {
      "List": [],
      "EmptyListItem": ""
    },
    "WorkoutComponentResults": {
      "List": [],
      "EmptyListItem": {
        "ClassId": "0",
        "StartTime": "",
        "HasResultsForClass": false,
        "PerformanceResultId": "0",
        "FullyFormattedResult": "",
        "IsRx": false,
        "IsRxPlus": false,
        "HasBeenScored": false
      }
    },
    "HasPerformedAtLeastOnce": false,
    "HasAtLeastOneWorkoutComponentResult": false
  },
  {
    "Id": "91354061",
    "IsSection": false,
    "IsVideoURL": false,
    "IsImage": false,
    "IsWarmup": false,
    "IsGymnastics": false,
    "IsWeightlifting": false,
    "IsMetcon": true,
    "IsWeightliftingTotal": false,
    "Name": "Accessories  160424",
    "Comment": "",
    "VideoURL": "",
    "VideoURLComment": "",
    "ImageURL": "",
    "ImageFilename": "",
    "ImageComment": "",
    "PrefixText": "",
    "MeasureIsMaxEffort": false,
    "MeasureRepScheme": "",
    "Description": "<p><span style=\"background-color:rgb(255,255,255);color:rgb(62,62,63);font-size:14px;\">3 rounds for quality of:</span></p><p><br><span style=\"background-color:rgb(255,255,255);color:rgb(62,62,63);font-size:14px;\">12 Chest Supported Trap-3 Raises, pick load</span></p><p><br><span style=\"background-color:rgb(255,255,255);color:rgb(62,62,63);font-size:14px;\">10 L/10 R Single Arm Dumbbell Bent Over Rows, pick load</span></p><p><br><span style=\"background-color:rgb(255,255,255);color:rgb(62,62,63);font-size:14px;\">Hollow Hold, 30 secs</span></p><p> </p><ul><li><a target=\"_blank\" rel=\"noopener noreferrer\" href=\"https://youtu.be/ax9Gg8djfig\">Trap 3 Raise</a></li></ul>",
    "Rounds": 0,
    "ResultTypeId": 13,
    "IsResultTypeEachRound": false,
    "IsResultTypeNoMeasure": false,
    "IsResultTypeCheckmark": true,
    "EachRoundTypeLabel": "",
    "ScalingId": 1,
    "ComponentId": "36145785",
    "ComponentExternalURL": "",
    "ComponentSystemComment": "",
    "TotalWeightLiftingComponents": {
      "List": [],
      "EmptyListItem": ""
    },
    "WorkoutComponentResults": {
      "List": [],
      "EmptyListItem": {
        "ClassId": "0",
        "StartTime": "",
        "HasResultsForClass": false,
        "PerformanceResultId": "0",
        "FullyFormattedResult": "",
        "IsRx": false,
        "IsRxPlus": false,
        "HasBeenScored": false
      }
    },
    "HasPerformedAtLeastOnce": false,
    "HasAtLeastOneWorkoutComponentResult": false
  }
]